seo_check_os_version-0.3.3.dist-info/METADATA
seo_check_os_version-0.3.3.dist-info/WHEEL
seo_check_os_version-0.3.3.dist-info/entry_points.txt
seo_check_os_version/.hi.py.swp
seo_check_os_version/__init__.py
seo_check_os_version/hi.py
seo_check_os_version-0.3.3.dist-info/RECORD
